steemengine/__init__.py
steemengine/api.py
steemengine/cli.py
steemengine/exceptions.py
steemengine/market.py
steemengine/rpc.py
steemengine/tokenobject.py
steemengine/tokens.py
steemengine/version.py
steemengine/wallet.py
steemengine-0.5.3.dist-info/LICENSE
steemengine-0.5.3.dist-info/METADATA
steemengine-0.5.3.dist-info/WHEEL
steemengine-0.5.3.dist-info/entry_points.txt
steemengine-0.5.3.dist-info/top_level.txt
steemengine-0.5.3.dist-info/RECORD
