Metadata-Version: 1.2
Name: steemengine
Version: 0.5.3
Summary: command line tool and python library for sending steem engine tokens
Home-page: UNKNOWN
Author: Holger Nahrstaedt
Author-email: holgernahrstaedt@gmx.de
Maintainer: Holger Nahrstaedt
Maintainer-email: holgernahrstaedt@gmx.de
License: UNKNOWN
Keywords: steem,tools
Platform: UNKNOWN
Classifier: License :: OSI Approved :: MIT License
Classifier: Operating System :: OS Independent
Classifier: Programming Language :: Python
Classifier: Programming Language :: Python :: 2.7
Classifier: Programming Language :: Python :: 3
Classifier: Programming Language :: Python :: 3.4
Classifier: Programming Language :: Python :: 3.5
Classifier: Programming Language :: Python :: 3.6
Classifier: Development Status :: 4 - Beta
Classifier: Intended Audience :: Developers
